modoboa/__init__.py
modoboa/test_settings.py
modoboa/urls.py
modoboa/urls_api_v1.py
modoboa/urls_api_v2.py
modoboa/version.py
modoboa/admin/__init__.py
modoboa/admin/app_settings.py
modoboa/admin/apps.py
modoboa/admin/constants.py
modoboa/admin/factories.py
modoboa/admin/handlers.py
modoboa/admin/lib.py
modoboa/admin/postfix_maps.py
modoboa/admin/signals.py
modoboa/admin/api/__init__.py
modoboa/admin/api/v1/__init__.py
modoboa/admin/api/v1/serializers.py
modoboa/admin/api/v1/tests.py
modoboa/admin/api/v1/urls.py
modoboa/admin/api/v1/viewsets.py
modoboa/admin/api/v2/__init__.py
modoboa/admin/api/v2/serializers.py
modoboa/admin/api/v2/tests.py
modoboa/admin/api/v2/urls.py
modoboa/admin/api/v2/viewsets.py
modoboa/admin/management/__init__.py
modoboa/admin/management/commands/__init__.py
modoboa/admin/management/commands/handle_mailbox_operations.py
modoboa/admin/management/commands/modo.py
modoboa/admin/management/commands/subcommands/__init__.py
modoboa/admin/management/commands/subcommands/_export.py
modoboa/admin/management/commands/subcommands/_import.py
modoboa/admin/management/commands/subcommands/_manage_dkim_keys.py
modoboa/admin/management/commands/subcommands/_mx.py
modoboa/admin/management/commands/subcommands/_repair.py
modoboa/admin/migrations/0001_initial.py
modoboa/admin/migrations/0002_migrate_from_modoboa_admin.py
modoboa/admin/migrations/0003_auto_20151118_1215.py
modoboa/admin/migrations/0004_auto_20160914_0907.py
modoboa/admin/migrations/0005_auto_20161026_1003.py
modoboa/admin/migrations/0006_auto_20161104_1900.py
modoboa/admin/migrations/0007_auto_20161104_1915.py
modoboa/admin/migrations/0008_domain_enable_dns_checks.py
modoboa/admin/migrations/0009_auto_20170215_0948.py
modoboa/admin/migrations/0010_auto_20170215_1328.py
modoboa/admin/migrations/0011_domain_transport.py
modoboa/admin/migrations/0012_auto_20180112_1658.py
modoboa/admin/migrations/0013_auto_20180124_2311.py
modoboa/admin/migrations/0014_auto_20181017_1628.py
modoboa-2.6.3.dist-info/licenses/LICENSE
modoboa-2.6.3.dist-info/METADATA
modoboa-2.6.3.dist-info/WHEEL
modoboa-2.6.3.dist-info/entry_points.txt
modoboa-2.6.3.dist-info/top_level.txt
modoboa-2.6.3.dist-info/RECORD
