Metadata-Version: 2.4
Name: modoboa
Version: 2.6.3
Summary: Mail hosting made simple
Author-email: Antoine Nguyen <tonio@ngyn.org>
License: ISC License
Project-URL: Homepage, http://modoboa.org/
Project-URL: Documentation, https://modoboa.readthedocs.io/en/latest/
Project-URL: Repository, https://github.com/modoboa/modoboa
Project-URL: Changelog, https://github.com/modoboa/modoboa/blob/master/CHANGELOG.md
Project-URL: Issues, https://github.com/modoboa/modoboa/issues
Keywords: email
Classifier: Development Status :: 5 - Production/Stable
Classifier: Environment :: Web Environment
Classifier: Framework :: Django :: 5.2
Classifier: Intended Audience :: System Administrators
Classifier: License :: OSI Approved :: ISC License (ISCL)
Classifier: Operating System :: OS Independent
Classifier: Programming Language :: Python :: 3.10
Classifier: Programming Language :: Python :: 3.11
Classifier: Programming Language :: Python :: 3.12
Classifier: Programming Language :: Python :: 3.13
Classifier: Topic :: Communications :: Email
Classifier: Topic :: Internet :: WWW/HTTP
Requires-Python: >=3.10
License-File: LICENSE
Requires-Dist: django==5.2.8
Requires-Dist: django-phonenumber-field[phonenumbers]==8.3.0
Requires-Dist: django-reversion==6.0.0
Requires-Dist: django-xforwardedfor-middleware==2.0
Requires-Dist: django-otp==1.6.3
Requires-Dist: django-filter
Requires-Dist: django-rename-app==0.1.7
Requires-Dist: django-environ
Requires-Dist: dj-database-url
Requires-Dist: djangorestframework<3.17,>=3.16
Requires-Dist: drf-spectacular
Requires-Dist: uritemplate
Requires-Dist: django-oauth-toolkit
Requires-Dist: django-cors-headers
Requires-Dist: passlib~=1.7.4
Requires-Dist: bcrypt==4.3.0
Requires-Dist: asgiref
Requires-Dist: dnspython==2.8.0
Requires-Dist: feedparser==6.0.12
Requires-Dist: fido2==2.0.0
Requires-Dist: gevent==25.9.1
Requires-Dist: progressbar33==2.4
Requires-Dist: python-dateutil
Requires-Dist: cryptography
Requires-Dist: pytz
Requires-Dist: requests
Requires-Dist: lxml_html_clean
Requires-Dist: chardet
Requires-Dist: ovh
Requires-Dist: oath
Requires-Dist: packaging
Requires-Dist: redis>=4.2.0rc1
Requires-Dist: rrdtool-bindings>=0.2.0
Requires-Dist: qrcode
Requires-Dist: aiosmtplib
Requires-Dist: reportlab
Requires-Dist: tldextract>=2.0.2
Requires-Dist: defusedxml>=0.6.0
Requires-Dist: python-magic>=0.4.24
Requires-Dist: rq>=1.13.0
Requires-Dist: django-rq
Requires-Dist: sievelib>=1.4.1
Requires-Dist: drf-nested-routers
Requires-Dist: vobject
Requires-Dist: caldav==2.1.2
Requires-Dist: html2text
Requires-Dist: idna
Provides-Extra: dev
Requires-Dist: django-debug-toolbar; extra == "dev"
Requires-Dist: pre-commit; extra == "dev"
Requires-Dist: black; extra == "dev"
Requires-Dist: ruff; extra == "dev"
Requires-Dist: django-extensions; extra == "dev"
Requires-Dist: Werkzeug; extra == "dev"
Requires-Dist: pyOpenSSL; extra == "dev"
Provides-Extra: mysql
Requires-Dist: mysqlclient<2.2.8; extra == "mysql"
Provides-Extra: postgresql
Requires-Dist: psycopg[binary]>=3.1; extra == "postgresql"
Provides-Extra: test
Requires-Dist: argon2-cffi>=16.1.0; extra == "test"
Requires-Dist: factory-boy<3.4.0; extra == "test"
Requires-Dist: httmock==1.4.0; extra == "test"
Requires-Dist: testfixtures==8.3.0; extra == "test"
Requires-Dist: tox; extra == "test"
Provides-Extra: ldap
Requires-Dist: django-auth-ldap<6.0.0; extra == "ldap"
Dynamic: license-file
